hegemos/__init__.py
hegemos-0.0.1.dist-info/METADATA
hegemos-0.0.1.dist-info/WHEEL
hegemos-0.0.1.dist-info/top_level.txt
hegemos-0.0.1.dist-info/RECORD
